{
  "project_info": {
    "project_number": "53232425094",
    "project_id": "lawyer-app-a9af7",
    "storage_bucket": "lawyer-app-a9af7.firebasestorage.app"
  },
  "client": [
    {
      "client_info": {
        "mobilesdk_app_id": "1:53232425094:android:b404eee28e321b5d561907",
        "android_client_info": {
          "package_name": "com.example.lawyer_app"
        }
      },
      "oauth_client": [],
      "api_key": [
        {
          "current_key": "AIzaSyADBdW1JUbgk9sKyDssqeGSwqHjBWS9MrA"
        }
      ],
      "services": {
        "appinvite_service": {
          "other_platform_oauth_client": []
        }
      }
    }
  ],
  "configuration_version": "1"
}